// class version 50.0 (50)
// access flags 0x401
public abstract class TConduit$$0$class {


  // access flags 0x9
  public static $init$(LTConduit$$0;)V
    RETURN
    MAXSTACK = 1
    MAXLOCALS = 1

  // access flags 0x9
  public static bindPart(LTConduit$$0;Lcodechicken/multipart/TMultiPart;)V
    ALOAD 0
    ALOAD 1
    INVOKEINTERFACE TConduit$$0.TConduit$$0$$super$bindPart (Lcodechicken/multipart/TMultiPart;)V
    ALOAD 1
    INSTANCEOF thermalexpansion/part/conduit/IConduit
    IFEQ L0
    ALOAD 0
    ALOAD 1
    CHECKCAST thermalexpansion/part/conduit/IConduit
    INVOKEINTERFACE TConduit$$0.TConduit$$0$$impl_$eq (Lthermalexpansion/part/conduit/IConduit;)V
   L0
   FRAME SAME
    RETURN
    MAXSTACK = 2
    MAXLOCALS = 2

  // access flags 0x9
  public static partRemoved(LTConduit$$0;Lcodechicken/multipart/TMultiPart;I)V
    ALOAD 0
    ALOAD 1
    ILOAD 2
    INVOKEINTERFACE TConduit$$0.TConduit$$0$$super$partRemoved (Lcodechicken/multipart/TMultiPart;I)V
    ALOAD 1
    ALOAD 0
    INVOKEINTERFACE TConduit$$0.TConduit$$0$$impl ()Lthermalexpansion/part/conduit/IConduit;
    IF_ACMPNE L0
    ALOAD 0
    ACONST_NULL
    INVOKEINTERFACE TConduit$$0.TConduit$$0$$impl_$eq (Lthermalexpansion/part/conduit/IConduit;)V
   L0
   FRAME SAME
    RETURN
    MAXSTACK = 3
    MAXLOCALS = 3

  // access flags 0x9
  public static canAddPart(LTConduit$$0;Lcodechicken/multipart/TMultiPart;)Z
    ALOAD 0
    INVOKEINTERFACE TConduit$$0.TConduit$$0$$impl ()Lthermalexpansion/part/conduit/IConduit;
    IFNULL L0
    ALOAD 1
    INSTANCEOF thermalexpansion/part/conduit/IConduit
    IFEQ L0
    ICONST_0
    IRETURN
   L0
   FRAME SAME
    ALOAD 0
    ALOAD 1
    INVOKEINTERFACE TConduit$$0.TConduit$$0$$super$canAddPart (Lcodechicken/multipart/TMultiPart;)Z
    IRETURN
    MAXSTACK = 2
    MAXLOCALS = 2

  // access flags 0x9
  public static isFluidConduit(LTConduit$$0;)Z
    ALOAD 0
    INVOKEINTERFACE TConduit$$0.TConduit$$0$$impl ()Lthermalexpansion/part/conduit/IConduit;
    INVOKEINTERFACE thermalexpansion/part/conduit/IConduit.isFluidConduit ()Z
    IRETURN
    MAXSTACK = 1
    MAXLOCALS = 1

  // access flags 0x9
  public static isEnergyConduit(LTConduit$$0;)I
    ALOAD 0
    INVOKEINTERFACE TConduit$$0.TConduit$$0$$impl ()Lthermalexpansion/part/conduit/IConduit;
    INVOKEINTERFACE thermalexpansion/part/conduit/IConduit.isEnergyConduit ()I
    IRETURN
    MAXSTACK = 1
    MAXLOCALS = 1

  // access flags 0x9
  public static getConduit(LTConduit$$0;)Lthermalexpansion/part/conduit/ConduitBase;
    ALOAD 0
    INVOKEINTERFACE TConduit$$0.TConduit$$0$$impl ()Lthermalexpansion/part/conduit/IConduit;
    INVOKEINTERFACE thermalexpansion/part/conduit/IConduit.getConduit ()Lthermalexpansion/part/conduit/ConduitBase;
    ARETURN
    MAXSTACK = 1
    MAXLOCALS = 1

  // access flags 0x9
  public static getConduitFluid(LTConduit$$0;)Lthermalexpansion/part/conduit/fluid/ConduitFluid;
    ALOAD 0
    INVOKEINTERFACE TConduit$$0.TConduit$$0$$impl ()Lthermalexpansion/part/conduit/IConduit;
    INVOKEINTERFACE thermalexpansion/part/conduit/IConduit.getConduitFluid ()Lthermalexpansion/part/conduit/fluid/ConduitFluid;
    ARETURN
    MAXSTACK = 1
    MAXLOCALS = 1

  // access flags 0x9
  public static isEnderConduit(LTConduit$$0;)Z
    ALOAD 0
    INVOKEINTERFACE TConduit$$0.TConduit$$0$$impl ()Lthermalexpansion/part/conduit/IConduit;
    INVOKEINTERFACE thermalexpansion/part/conduit/IConduit.isEnderConduit ()Z
    IRETURN
    MAXSTACK = 1
    MAXLOCALS = 1

  // access flags 0x9
  public static getConduitEnergy(LTConduit$$0;)Lthermalexpansion/part/conduit/energy/ConduitEnergy;
    ALOAD 0
    INVOKEINTERFACE TConduit$$0.TConduit$$0$$impl ()Lthermalexpansion/part/conduit/IConduit;
    INVOKEINTERFACE thermalexpansion/part/conduit/IConduit.getConduitEnergy ()Lthermalexpansion/part/conduit/energy/ConduitEnergy;
    ARETURN
    MAXSTACK = 1
    MAXLOCALS = 1

  // access flags 0x9
  public static getConduitItem(LTConduit$$0;)Lthermalexpansion/part/conduit/item/ConduitItem;
    ALOAD 0
    INVOKEINTERFACE TConduit$$0.TConduit$$0$$impl ()Lthermalexpansion/part/conduit/IConduit;
    INVOKEINTERFACE thermalexpansion/part/conduit/IConduit.getConduitItem ()Lthermalexpansion/part/conduit/item/ConduitItem;
    ARETURN
    MAXSTACK = 1
    MAXLOCALS = 1

  // access flags 0x9
  public static isItemConduit(LTConduit$$0;)Z
    ALOAD 0
    INVOKEINTERFACE TConduit$$0.TConduit$$0$$impl ()Lthermalexpansion/part/conduit/IConduit;
    INVOKEINTERFACE thermalexpansion/part/conduit/IConduit.isItemConduit ()Z
    IRETURN
    MAXSTACK = 1
    MAXLOCALS = 1

  // access flags 0x9
  public static copyFrom(LTConduit$$0;Lcodechicken/multipart/TileMultipart;)V
    ALOAD 0
    ALOAD 1
    INVOKEINTERFACE TConduit$$0.TConduit$$0$$super$copyFrom (Lcodechicken/multipart/TileMultipart;)V
    ALOAD 1
    INSTANCEOF TConduit$$0
    IFEQ L0
    ALOAD 0
    ALOAD 1
    INVOKEINTERFACE TConduit$$0.TConduit$$0$$impl ()Lthermalexpansion/part/conduit/IConduit;
    INVOKEINTERFACE TConduit$$0.TConduit$$0$$impl_$eq (Lthermalexpansion/part/conduit/IConduit;)V
   L0
    RETURN
    MAXSTACK = 2
    MAXLOCALS = 2
}
