// class version 50.0 (50)
// access flags 0x401
public abstract class TRedstoneControl$$2$class {


  // access flags 0x9
  public static $init$(LTRedstoneControl$$2;)V
    RETURN
    MAXSTACK = 1
    MAXLOCALS = 1

  // access flags 0x9
  public static bindPart(LTRedstoneControl$$2;Lcodechicken/multipart/TMultiPart;)V
    ALOAD 0
    ALOAD 1
    INVOKEINTERFACE TRedstoneControl$$2.TRedstoneControl$$2$$super$bindPart (Lcodechicken/multipart/TMultiPart;)V
    ALOAD 1
    INSTANCEOF cofh/api/tileentity/IRedstoneControl
    IFEQ L0
    ALOAD 0
    ALOAD 1
    CHECKCAST cofh/api/tileentity/IRedstoneControl
    INVOKEINTERFACE TRedstoneControl$$2.TRedstoneControl$$2$$impl_$eq (Lcofh/api/tileentity/IRedstoneControl;)V
   L0
   FRAME SAME
    RETURN
    MAXSTACK = 2
    MAXLOCALS = 2

  // access flags 0x9
  public static partRemoved(LTRedstoneControl$$2;Lcodechicken/multipart/TMultiPart;I)V
    ALOAD 0
    ALOAD 1
    ILOAD 2
    INVOKEINTERFACE TRedstoneControl$$2.TRedstoneControl$$2$$super$partRemoved (Lcodechicken/multipart/TMultiPart;I)V
    ALOAD 1
    ALOAD 0
    INVOKEINTERFACE TRedstoneControl$$2.TRedstoneControl$$2$$impl ()Lcofh/api/tileentity/IRedstoneControl;
    IF_ACMPNE L0
    ALOAD 0
    ACONST_NULL
    INVOKEINTERFACE TRedstoneControl$$2.TRedstoneControl$$2$$impl_$eq (Lcofh/api/tileentity/IRedstoneControl;)V
   L0
   FRAME SAME
    RETURN
    MAXSTACK = 3
    MAXLOCALS = 3

  // access flags 0x9
  public static canAddPart(LTRedstoneControl$$2;Lcodechicken/multipart/TMultiPart;)Z
    ALOAD 0
    INVOKEINTERFACE TRedstoneControl$$2.TRedstoneControl$$2$$impl ()Lcofh/api/tileentity/IRedstoneControl;
    IFNULL L0
    ALOAD 1
    INSTANCEOF cofh/api/tileentity/IRedstoneControl
    IFEQ L0
    ICONST_0
    IRETURN
   L0
   FRAME SAME
    ALOAD 0
    ALOAD 1
    INVOKEINTERFACE TRedstoneControl$$2.TRedstoneControl$$2$$super$canAddPart (Lcodechicken/multipart/TMultiPart;)Z
    IRETURN
    MAXSTACK = 2
    MAXLOCALS = 2

  // access flags 0x9
  public static handlePowerUpdate(LTRedstoneControl$$2;Z)V
    ALOAD 0
    INVOKEINTERFACE TRedstoneControl$$2.TRedstoneControl$$2$$impl ()Lcofh/api/tileentity/IRedstoneControl;
    ILOAD 1
    INVOKEINTERFACE cofh/api/tileentity/IRedstoneControl.handlePowerUpdate (Z)V
    RETURN
    MAXSTACK = 2
    MAXLOCALS = 2

  // access flags 0x9
  public static isPowered(LTRedstoneControl$$2;)Z
    ALOAD 0
    INVOKEINTERFACE TRedstoneControl$$2.TRedstoneControl$$2$$impl ()Lcofh/api/tileentity/IRedstoneControl;
    INVOKEINTERFACE cofh/api/tileentity/IRedstoneControl.isPowered ()Z
    IRETURN
    MAXSTACK = 1
    MAXLOCALS = 1

  // access flags 0x9
  public static handleConfigUpdate(LTRedstoneControl$$2;ZZ)V
    ALOAD 0
    INVOKEINTERFACE TRedstoneControl$$2.TRedstoneControl$$2$$impl ()Lcofh/api/tileentity/IRedstoneControl;
    ILOAD 1
    ILOAD 2
    INVOKEINTERFACE cofh/api/tileentity/IRedstoneControl.handleConfigUpdate (ZZ)V
    RETURN
    MAXSTACK = 3
    MAXLOCALS = 3

  // access flags 0x9
  public static setControlDisable(LTRedstoneControl$$2;Z)Z
    ALOAD 0
    INVOKEINTERFACE TRedstoneControl$$2.TRedstoneControl$$2$$impl ()Lcofh/api/tileentity/IRedstoneControl;
    ILOAD 1
    INVOKEINTERFACE cofh/api/tileentity/IRedstoneControl.setControlDisable (Z)Z
    IRETURN
    MAXSTACK = 2
    MAXLOCALS = 2

  // access flags 0x9
  public static getControlDisable(LTRedstoneControl$$2;)Z
    ALOAD 0
    INVOKEINTERFACE TRedstoneControl$$2.TRedstoneControl$$2$$impl ()Lcofh/api/tileentity/IRedstoneControl;
    INVOKEINTERFACE cofh/api/tileentity/IRedstoneControl.getControlDisable ()Z
    IRETURN
    MAXSTACK = 1
    MAXLOCALS = 1

  // access flags 0x9
  public static getControlSetting(LTRedstoneControl$$2;)Z
    ALOAD 0
    INVOKEINTERFACE TRedstoneControl$$2.TRedstoneControl$$2$$impl ()Lcofh/api/tileentity/IRedstoneControl;
    INVOKEINTERFACE cofh/api/tileentity/IRedstoneControl.getControlSetting ()Z
    IRETURN
    MAXSTACK = 1
    MAXLOCALS = 1

  // access flags 0x9
  public static setControlSetting(LTRedstoneControl$$2;Z)Z
    ALOAD 0
    INVOKEINTERFACE TRedstoneControl$$2.TRedstoneControl$$2$$impl ()Lcofh/api/tileentity/IRedstoneControl;
    ILOAD 1
    INVOKEINTERFACE cofh/api/tileentity/IRedstoneControl.setControlSetting (Z)Z
    IRETURN
    MAXSTACK = 2
    MAXLOCALS = 2

  // access flags 0x9
  public static setRedstoneConfig(LTRedstoneControl$$2;ZZ)Z
    ALOAD 0
    INVOKEINTERFACE TRedstoneControl$$2.TRedstoneControl$$2$$impl ()Lcofh/api/tileentity/IRedstoneControl;
    ILOAD 1
    ILOAD 2
    INVOKEINTERFACE cofh/api/tileentity/IRedstoneControl.setRedstoneConfig (ZZ)Z
    IRETURN
    MAXSTACK = 3
    MAXLOCALS = 3

  // access flags 0x9
  public static copyFrom(LTRedstoneControl$$2;Lcodechicken/multipart/TileMultipart;)V
    ALOAD 0
    ALOAD 1
    INVOKEINTERFACE TRedstoneControl$$2.TRedstoneControl$$2$$super$copyFrom (Lcodechicken/multipart/TileMultipart;)V
    ALOAD 1
    INSTANCEOF TRedstoneControl$$2
    IFEQ L0
    ALOAD 0
    ALOAD 1
    INVOKEINTERFACE TRedstoneControl$$2.TRedstoneControl$$2$$impl ()Lcofh/api/tileentity/IRedstoneControl;
    INVOKEINTERFACE TRedstoneControl$$2.TRedstoneControl$$2$$impl_$eq (Lcofh/api/tileentity/IRedstoneControl;)V
   L0
    RETURN
    MAXSTACK = 2
    MAXLOCALS = 2
}
