// class version 50.0 (50)
// access flags 0x401
public abstract class TTileInfo$$4$class {


  // access flags 0x9
  public static $init$(LTTileInfo$$4;)V
    RETURN
    MAXSTACK = 1
    MAXLOCALS = 1

  // access flags 0x9
  public static bindPart(LTTileInfo$$4;Lcodechicken/multipart/TMultiPart;)V
    ALOAD 0
    ALOAD 1
    INVOKEINTERFACE TTileInfo$$4.TTileInfo$$4$$super$bindPart (Lcodechicken/multipart/TMultiPart;)V
    ALOAD 1
    INSTANCEOF cofh/block/ITileInfo
    IFEQ L0
    ALOAD 0
    ALOAD 1
    CHECKCAST cofh/block/ITileInfo
    INVOKEINTERFACE TTileInfo$$4.TTileInfo$$4$$impl_$eq (Lcofh/block/ITileInfo;)V
   L0
   FRAME SAME
    RETURN
    MAXSTACK = 2
    MAXLOCALS = 2

  // access flags 0x9
  public static partRemoved(LTTileInfo$$4;Lcodechicken/multipart/TMultiPart;I)V
    ALOAD 0
    ALOAD 1
    ILOAD 2
    INVOKEINTERFACE TTileInfo$$4.TTileInfo$$4$$super$partRemoved (Lcodechicken/multipart/TMultiPart;I)V
    ALOAD 1
    ALOAD 0
    INVOKEINTERFACE TTileInfo$$4.TTileInfo$$4$$impl ()Lcofh/block/ITileInfo;
    IF_ACMPNE L0
    ALOAD 0
    ACONST_NULL
    INVOKEINTERFACE TTileInfo$$4.TTileInfo$$4$$impl_$eq (Lcofh/block/ITileInfo;)V
   L0
   FRAME SAME
    RETURN
    MAXSTACK = 3
    MAXLOCALS = 3

  // access flags 0x9
  public static canAddPart(LTTileInfo$$4;Lcodechicken/multipart/TMultiPart;)Z
    ALOAD 0
    INVOKEINTERFACE TTileInfo$$4.TTileInfo$$4$$impl ()Lcofh/block/ITileInfo;
    IFNULL L0
    ALOAD 1
    INSTANCEOF cofh/block/ITileInfo
    IFEQ L0
    ICONST_0
    IRETURN
   L0
   FRAME SAME
    ALOAD 0
    ALOAD 1
    INVOKEINTERFACE TTileInfo$$4.TTileInfo$$4$$super$canAddPart (Lcodechicken/multipart/TMultiPart;)Z
    IRETURN
    MAXSTACK = 2
    MAXLOCALS = 2

  // access flags 0x9
  public static getTileInfo(LTTileInfo$$4;Ljava/util/List;Lnet/minecraftforge/common/ForgeDirection;Lnet/minecraft/entity/player/EntityPlayer;Z)V
    ALOAD 0
    INVOKEINTERFACE TTileInfo$$4.TTileInfo$$4$$impl ()Lcofh/block/ITileInfo;
    ALOAD 1
    ALOAD 2
    ALOAD 3
    ILOAD 4
    INVOKEINTERFACE cofh/block/ITileInfo.getTileInfo (Ljava/util/List;Lnet/minecraftforge/common/ForgeDirection;Lnet/minecraft/entity/player/EntityPlayer;Z)V
    RETURN
    MAXSTACK = 5
    MAXLOCALS = 5

  // access flags 0x9
  public static copyFrom(LTTileInfo$$4;Lcodechicken/multipart/TileMultipart;)V
    ALOAD 0
    ALOAD 1
    INVOKEINTERFACE TTileInfo$$4.TTileInfo$$4$$super$copyFrom (Lcodechicken/multipart/TileMultipart;)V
    ALOAD 1
    INSTANCEOF TTileInfo$$4
    IFEQ L0
    ALOAD 0
    ALOAD 1
    INVOKEINTERFACE TTileInfo$$4.TTileInfo$$4$$impl ()Lcofh/block/ITileInfo;
    INVOKEINTERFACE TTileInfo$$4.TTileInfo$$4$$impl_$eq (Lcofh/block/ITileInfo;)V
   L0
    RETURN
    MAXSTACK = 2
    MAXLOCALS = 2
}
